[
    {
        "data": {
            "threaded_conversation_with_injections_v2": {
                "instructions": [
                    {
                        "type": "TimelineAddEntries",
                        "entries": [
                            {
                                "entryId": "tweet-1894746077724807523",
                                "sortIndex": "7328625959129968284",
                                "content": {
                                    "entryType": "TimelineTimelineItem",
                                    "__typename": "TimelineTimelineItem",
                                    "itemContent": {
                                        "itemType": "TimelineTweet",
                                        "__typename": "TimelineTweet",
                                        "tweet_results": {
                                            "result": {
                                                "__typename": "Tweet",
                                                "rest_id": "1894746077724807523",
                                                "has_birdwatch_notes": false,
                                                "core": {
                                                    "user_results": {
                                                        "result": {
                                                            "__typename": "User",
                                                            "id": "VXNlcjoxODgxNjg5Njg5MzQzODAzMzky",
                                                            "rest_id": "1881689689343803392",
                                                            "affiliates_highlighted_label": {},
                                                            "has_graduated_access": true,
                                                            "parody_commentary_fan_label": "None",
                                                            "is_blue_verified": false,
                                                            "profile_image_shape": "Circle",
                                                            "legacy": {
                                                                "following": false,
                                                                "can_dm": false,
                                                                "can_media_tag": true,
                                                                "created_at": "Tue Jan 21 13:07:09 +0000 2025",
                                                                "default_profile": true,
                                                                "default_profile_image": false,
                                                                "description": "Explore my latest NFTs: Exploring futuristic Nexus Lumen art on raribal #digitalpainting #abstractart #NexusLumen\nTeligram|\ud83d\udc49https://t.co/zPq8ZemPr9",
                                                                "entities": {
                                                                    "description": {
                                                                        "urls": [
                                                                            {
                                                                                "display_url": "t.me/DIGITALZenNFTs",
                                                                                "expanded_url": "https://t.me/DIGITALZenNFTs",
                                                                                "url": "https://t.co/zPq8ZemPr9",
                                                                                "indices": [
                                                                                    124,
                                                                                    147
                                                                                ]
                                                                            }
                                                                        ]
                                                                    },
                                                                    "url": {
                                                                        "urls": [
                                                                            {
                                                                                "display_url": "rarible.com/digitalzen",
                                                                                "expanded_url": "https://rarible.com/digitalzen",
                                                                                "url": "https://t.co/0gxm85FkK7",
                                                                                "indices": [
                                                                                    0,
                                                                                    23
                                                                                ]
                                                                            }
                                                                        ]
                                                                    }
                                                                },
                                                                "fast_followers_count": 0,
                                                                "favourites_count": 76,
                                                                "followers_count": 14,
                                                                "friends_count": 5,
                                                                "has_custom_timelines": false,
                                                                "is_translator": false,
                                                                "listed_count": 0,
                                                                "location": "\ud83e\udee1\ud83c\uddee\ud83c\uddf3\ud83d\udc40",
                                                                "media_count": 126,
                                                                "name": "Zen NFTs",
                                                                "normal_followers_count": 14,
                                                                "pinned_tweet_ids_str": [],
                                                                "possibly_sensitive": false,
                                                                "profile_banner_url": "https://pbs.twimg.com/profile_banners/1881689689343803392/1740562855",
                                                                "profile_image_url_https": "https://pbs.twimg.com/profile_images/1894402219887529991/qHjNPQBo_normal.jpg",
                                                                "profile_interstitial_type": "",
                                                                "screen_name": "DIGITALZen",
                                                                "statuses_count": 735,
                                                                "translator_type": "none",
                                                                "url": "https://t.co/0gxm85FkK7",
                                                                "verified": false,
                                                                "want_retweets": false,
                                                                "withheld_in_countries": []
                                                            },
                                                            "professional": {
                                                                "rest_id": "1881691428579152069",
                                                                "professional_type": "Creator",
                                                                "category": [
                                                                    {
                                                                        "id": 1017,
                                                                        "name": "Artist",
                                                                        "icon_name": "IconBriefcaseStroke"
                                                                    }
                                                                ]
                                                            },
                                                            "tipjar_settings": {}
                                                        }
                                                    }
                                                },
                                                "card": {
                                                    "rest_id": "https://t.co/BjgpRDiQBs",
                                                    "legacy": {
                                                        "binding_values": [
                                                            {
                                                                "key": "description",
                                                                "value": {
                                                                    "string_value": "Discover, sell and buy NFTs on Rarible! Our aggregated NFT marketplace for Ethereum NFTs and Polygon NFTs powers brands, collections and creator marketplaces.",
                                                                    "type": "STRING"
                                                                }
                                                            },
                                                            {
                                                                "key": "domain",
                                                                "value": {
                                                                    "string_value": "rarible.com",
                                                                    "type": "STRING"
                                                                }
                                                            },
                                                            {
                                                                "key": "vanity_url",
                                                                "value": {
                                                                    "scribe_key": "vanity_url",
                                                                    "string_value": "rarible.com",
                                                                    "type": "STRING"
                                                                }
                                                            },
                                                            {
                                                                "key": "title",
                                                                "value": {
                                                                    "string_value": "Untitled",
                                                                    "type": "STRING"
                                                                }
                                                            },
                                                            {
                                                                "key": "card_url",
                                                                "value": {
                                                                    "scribe_key": "card_url",
                                                                    "string_value": "https://t.co/BjgpRDiQBs",
                                                                    "type": "STRING"
                                                                }
                                                            }
                                                        ],
                                                        "card_platform": {
                                                            "platform": {
                                                                "audience": {
                                                                    "name": "production"
                                                                },
                                                                "device": {
                                                                    "name": "Swift",
                                                                    "version": "12"
                                                                }
                                                            }
                                                        },
                                                        "name": "summary_large_image",
                                                        "url": "https://t.co/BjgpRDiQBs",
                                                        "user_refs_results": []
                                                    }
                                                },
                                                "unmention_data": {},
                                                "edit_control": {
                                                    "edit_tweet_ids": [
                                                        "1894746077724807523"
                                                    ],
                                                    "editable_until_msecs": "1740581242000",
                                                    "is_edit_eligible": true,
                                                    "edits_remaining": "5"
                                                },
                                                "is_translatable": false,
                                                "views": {
                                                    "count": "13",
                                                    "state": "EnabledWithCount"
                                                },
                                                "source": "<a href=\"http://twitter.com/download/android\" rel=\"nofollow\">Twitter for Android</a>",
                                                "grok_analysis_button": false,
                                                "legacy": {
                                                    "bookmark_count": 0,
                                                    "bookmarked": false,
                                                    "created_at": "Wed Feb 26 13:47:22 +0000 2025",
                                                    "conversation_id_str": "1894746077724807523",
                                                    "display_text_range": [
                                                        0,
                                                        89
                                                    ],
                                                    "entities": {
                                                        "hashtags": [
                                                            {
                                                                "indices": [
                                                                    68,
                                                                    76
                                                                ],
                                                                "text": "rarible"
                                                            }
                                                        ],
                                                        "symbols": [],
                                                        "timestamps": [],
                                                        "urls": [
                                                            {
                                                                "display_url": "rarible.com/token/0xc91544\u2026",
                                                                "expanded_url": "https://rarible.com/token/0xc9154424b823b10579895ccbe442d41b9abd96ed:56809567414171181934060656113803967437018658182747006741012445956068698227225",
                                                                "url": "https://t.co/BjgpRDiQBs",
                                                                "indices": [
                                                                    44,
                                                                    67
                                                                ]
                                                            }
                                                        ],
                                                        "user_mentions": [
                                                            {
                                                                "id_str": "1160222700104757249",
                                                                "name": "Rarible",
                                                                "screen_name": "rarible",
                                                                "indices": [
                                                                    81,
                                                                    89
                                                                ]
                                                            }
                                                        ]
                                                    },
                                                    "favorite_count": 0,
                                                    "favorited": false,
                                                    "full_text": "I've just created \"Oculus Zen\" collectible! https://t.co/BjgpRDiQBs #rarible via @rarible",
                                                    "is_quote_status": false,
                                                    "lang": "en",
                                                    "possibly_sensitive": false,
                                                    "possibly_sensitive_editable": true,
                                                    "quote_count": 0,
                                                    "reply_count": 0,
                                                    "retweet_count": 0,
                                                    "retweeted": false,
                                                    "user_id_str": "1881689689343803392",
                                                    "id_str": "1894746077724807523"
                                                },
                                                "quick_promote_eligibility": {
                                                    "eligibility": "IneligibleNotProfessional"
                                                }
                                            }
                                        },
                                        "tweetDisplayType": "Tweet",
                                        "hasModeratedReplies": false
                                    }
                                }
                            }
                        ]
                    },
                    {
                        "type": "TimelineTerminateTimeline",
                        "direction": "Top"
                    }
                ]
            }
        }
    }
]